tractor_beam/__init__.py
tractor_beam/processor.py
tractor_beam/tractor.py
tractor_beam/abducts/__init__.py
tractor_beam/abducts/abduct.py
tractor_beam/abducts/beacons/__init__.py
tractor_beam/abducts/beacons/edgar.py
tractor_beam/abducts/beacons/google.py
tractor_beam/abducts/beacons/youtube.py
tractor_beam/utils/__init__.py
tractor_beam/utils/config.py
tractor_beam/utils/file_handlers.py
tractor_beam/utils/globals.py
tractor_beam/utils/quantum.py
tractor_beam/visits/__init__.py
tractor_beam/visits/visit.py
llm_tractor_beam-0.1.2.dist-info/LICENSE
llm_tractor_beam-0.1.2.dist-info/METADATA
llm_tractor_beam-0.1.2.dist-info/WHEEL
llm_tractor_beam-0.1.2.dist-info/top_level.txt
llm_tractor_beam-0.1.2.dist-info/RECORD
