Metadata-Version: 2.1
Name: llm_tractor_beam
Version: 0.1.2
Summary: An embedding model toolkit; fine-tune SOTA LLMs on knowledge bases rapidly.
Home-page: https://github.com/DylanAlloy/tractor-beam
License-File: LICENSE
